{
  "schema_version": "status_summary.v1",
  "projection_path": "docs/progress-tracker/state/status_summary.v1.json",
  "updated_at": "2026-04-22T22:31:32.069958Z",
  "source": {
    "generator": "progress_manager.load_status_summary_projection",
    "progress_path": "docs/progress-tracker/state/progress.json",
    "checkpoints_path": "docs/progress-tracker/state/checkpoints.json"
  },
  "inputs": {
    "progress": {
      "path": "docs/progress-tracker/state/progress.json",
      "exists": true,
      "mtime_ns": 1776852145588149555,
      "size": 90774
    },
    "checkpoints": {
      "path": "docs/progress-tracker/state/checkpoints.json",
      "exists": true,
      "mtime_ns": 1776862293787600231,
      "size": 5830
    }
  },
  "progress": {
    "completed": 27,
    "total": 28,
    "percentage": 96
  },
  "next_action": {
    "type": "feature",
    "feature_id": 27,
    "feature_name": "优化概念命名与映射：将 prog-sync 类比为 log，prog-update 类比为 note",
    "development_stage": "developing",
    "stage_label": "开发中"
  },
  "plan_health": {
    "status": "N/A",
    "plan_path": null,
    "message": "无活跃计划"
  },
  "risk_blocker": {
    "has_risk": false,
    "high_priority_bugs": 0,
    "blocked_count": 0,
    "message": "正常"
  },
  "recent_snapshot": {
    "exists": true,
    "timestamp": "2026-04-22T20:51:33.727681+08:00",
    "relative_time": "1 小时前"
  }
}